smtp_email_sender/__init__.py
smtp_email_sender/smtp_email_sender.py
smtp_email_sender-1.0.4.dist-info/LICENSE
smtp_email_sender-1.0.4.dist-info/METADATA
smtp_email_sender-1.0.4.dist-info/WHEEL
smtp_email_sender-1.0.4.dist-info/top_level.txt
smtp_email_sender-1.0.4.dist-info/RECORD
