Metadata-Version: 2.2
Name: smtp-email-sender
Version: 1.0.4
Summary: A simple email sender package with SMTP
Home-page: https://github.com/ErhanTurker01/SMTP-Email-Sender
Author: Erhan Turker
Author-email: erantrk0122@gmail.com
Classifier: Programming Language :: Python :: 3
Classifier: License :: OSI Approved :: MIT License
Classifier: Operating System :: OS Independent
Requires-Python: >=3.6
License-File: LICENSE
Dynamic: author
Dynamic: author-email
Dynamic: classifier
Dynamic: description
Dynamic: description-content-type
Dynamic: home-page
Dynamic: requires-python
Dynamic: summary
